setup.py
netease/__init__.py
netease/compat.py
netease/config.py
netease/download.py
netease/encrypt.py
netease/exceptions.py
netease/logger.py
netease/models.py
netease/start.py
netease/utils.py
netease/weapi.py
netease_dl.egg-info/PKG-INFO
netease_dl.egg-info/SOURCES.txt
netease_dl.egg-info/dependency_links.txt
netease_dl.egg-info/entry_points.txt
netease_dl.egg-info/requires.txt
netease_dl.egg-info/top_level.txt