Metadata-Version: 1.0
Name: netease-dl
Version: 1.0.2
Summary: 一个基于命令行的网易云音乐下载器
Home-page: https://github.com/ziwenxie/netease-dl
Author: ziwenxie
Author-email: ziwenxiecat@gmail.com
License: MIT
Keywords: music,netease,download,command tool
Platform: UNKNOWN
